mondialrelay_pyt/__init__.py
mondialrelay_pyt/mondialrelay_pyt.py
mondialrelay_pyt-0.2.2.dist-info/METADATA
mondialrelay_pyt-0.2.2.dist-info/WHEEL
mondialrelay_pyt-0.2.2.dist-info/top_level.txt
mondialrelay_pyt-0.2.2.dist-info/RECORD
