Metadata-Version: 2.1
Name: mondialrelay-pyt
Version: 0.2.2
Summary: A library to access Mondial Relay Web Service from Python.
Home-page: http://github.com/Bvr4/mondialrelay_pyt
Author: Aymeric Lecomte, Sebastien Beau, Henri Dewilde
Author-email: aymeric.lecomte@akretion.com, sebastien.beau@akretion.com, henri.dewilde@gmail.com
License: GNU AGPL-3
Keywords: mondial relay api client
Platform: UNKNOWN
Classifier: Development Status :: 4 - Beta
Classifier: Intended Audience :: Developers
Classifier: License :: OSI Approved :: GNU Affero General Public License v3
Classifier: Topic :: Software Development :: Libraries :: Python Modules
Classifier: Topic :: Internet :: WWW/HTTP :: Site Management
Classifier: Topic :: Internet
Requires-Dist: requests>=2.32.3
Requires-Dist: xmltodict>=0.14.2
